{"stat.chestOpened":38,"stat.useItem.minecraft.end_bricks":1,"stat.horseOneCm":3993,"stat.mineBlock.minecraft.netherrack":16,"stat.leaveGame":1,"stat.killEntity.Slime":3,"stat.useItem.minecraft.soul_sand":378,"stat.useItem.minecraft.diamond_sword":4,"stat.craftItem.minecraft.diamond_sword":1,"stat.swimOneCm":4487,"stat.jump":720,"stat.fallOneCm":7014,"stat.climbOneCm":2495,"stat.pickup.minecraft.cooked_porkchop":36,"stat.crouchOneCm":11153,"stat.pickup.minecraft.dirt":2,"stat.useItem.minecraft.dirt":2,"stat.useItem.minecraft.egg":1,"stat.damageTaken":230,"stat.tradedWithVillager":4,"stat.aviateOneCm":785872,"stat.flyOneCm":249312,"stat.craftItem.minecraft.iron_shovel":3,"stat.pickup.minecraft.soul_sand":1499,"stat.drop.minecraft.soul_sand":1057,"stat.damageDealt":220,"stat.timeSinceDeath":59872,"stat.pickup.minecraft.end_bricks":1,"stat.mineBlock.minecraft.dirt":2,"stat.useItem.minecraft.iron_shovel":937,"stat.walkOneCm":223320,"stat.trappedChestTriggered":23,"stat.useItem.minecraft.cooked_porkchop":5,"stat.talkedToVillager":63,"stat.pickup.minecraft.stone":90,"stat.mineBlock.minecraft.end_bricks":1,"stat.sprintOneCm":151777,"stat.useItem.minecraft.diamond_pickaxe":110,"stat.pickup.minecraft.emerald":49,"stat.mobKills":3,"stat.mineBlock.minecraft.soul_sand":937,"stat.drop":19,"stat.pickup.minecraft.egg":1,"stat.playOneMinute":59872,"stat.breakItem.minecraft.iron_shovel":1,"stat.sneakTime":4156,"stat.mineBlock.minecraft.stone":93,"stat.pickup.minecraft.netherrack":16,"stat.diveOneCm":9534}